akinoncli/__init__.py
akinoncli/main.py
akinoncli/client/__init__.py
akinoncli/client/client.py
akinoncli/controllers/__init__.py
akinoncli/controllers/account.py
akinoncli/controllers/applications.py
akinoncli/controllers/auth.py
akinoncli/controllers/base.py
akinoncli/controllers/projects.py
akinoncli/controllers/public_keys.py
akinoncli/core/__init__.py
akinoncli/core/exc.py
akinoncli/core/version.py
akinoncli/ext/__init__.py
akinoncli/ext/output_renderer.py
akinoncli/ext/update_checker.py
akinoncli-1.0.23.dist-info/LICENSE.md
akinoncli-1.0.23.dist-info/METADATA
akinoncli-1.0.23.dist-info/WHEEL
akinoncli-1.0.23.dist-info/entry_points.txt
akinoncli-1.0.23.dist-info/top_level.txt
akinoncli-1.0.23.dist-info/RECORD
