Metadata-Version: 2.1
Name: akinoncli
Version: 1.0.23
Summary: CLI for Akinon Cloud Commerce
Home-page: https://bitbucket.org/akinonteam/akinon-cli/
Author: Akinon
Author-email: dev@akinon.com
Maintainer: Akinon
Maintainer-email: dev@akinon.com
License: MIT
Platform: UNKNOWN
Classifier: Programming Language :: Python
Classifier: Programming Language :: Python :: 3
Classifier: Programming Language :: Python :: 3 :: Only
Classifier: Environment :: Console
License-File: LICENSE.md
Requires-Dist: cement ==3.0.4
Requires-Dist: pyyaml ==6.0.1
Requires-Dist: colorlog ==6.6.0
Requires-Dist: tinydb ==4.3.0
Requires-Dist: requests ==2.25.0
Requires-Dist: rich ==11.2.0
Requires-Dist: packaging ==21.3
